confirmations/__init__.py
confirmations-0.1.0.dist-info/METADATA
confirmations-0.1.0.dist-info/WHEEL
confirmations-0.1.0.dist-info/entry_points.txt
confirmations-0.1.0.dist-info/top_level.txt
confirmations-0.1.0.dist-info/RECORD
