Metadata-Version: 2.2
Name: confirmations
Version: 0.1.0
Summary: Fetch and analyze US Senate confirmation votes
Home-page: https://gitlab.com/emilesnyder/confirmations
Author: Emile Snyder
Author-email: emile.snyder@gmail.com
License: Public Domain
Classifier: Development Status :: 4 - Beta
Classifier: Environment :: Console
Classifier: Intended Audience :: End Users/Desktop
Classifier: License :: Public Domain
Classifier: Programming Language :: Python
Classifier: Topic :: Other/Nonlisted Topic
Requires-Dist: bs4
Requires-Dist: lxml
Requires-Dist: requests_cache
